1.ece284fa24_hw4/hardware/Rough work/mac_tile.v
// Created by prof. Mingu Kang @VVIP Lab in UCSD ECE department
// Please do not spread this code without permission


module mac_array_tb;

// Parameters
parameter bw = 4;
parameter psum_bw = 16;

// Testbench Signals
reg clk;
reg reset;
reg [bw-1:0] in_w;
reg [psum_bw-1:0] in_n;
reg [1:0] inst_w;
wire [psum_bw-1:0] out_s;
wire [bw-1:0] out_e;
wire [1:0] inst_e;

// Instantiate the DUT (Device Under Test)
mac_array #(
    .bw(bw),
    .psum_bw(psum_bw)
) dut (
    .clk(clk),
    .out_s(out_s),
    .in_w(in_w),
    .out_e(out_e),
    .in_n(in_n),
    .inst_w(inst_w),
    .inst_e(inst_e),
    .reset(reset)
);

// Clock generation
always #5 clk = ~clk;

// Stimulus
initial begin
    $dumpfile("mac_tb.vcd");
    $dumpvars(0,mac_array_tb);
    // Initialize inputs
    clk = 0;
    reset = 1;
    in_w = 4'hf;
    in_n = 0;
    inst_w = 0;

    // Apply reset
    #10;
    reset = 0;
    #10;
    reset = 1;
    #10 
    inst_w = 2'b01;
    #10
    in_w = 4'h1;
    #10
    in_w = 4'hc;
    #10
    in_w = 4'hd;
    #10
    in_w = 4'h9;
    #10
    in_w = 4'hf;
    #10
    in_w = 4'h1;
    #10
    reset = 1'b1;
    #20 $finish;
end

    // Test case 1: Load kernel (set inst

    endmodule



module mac_array (clk, out_s, in_w, out_e, in_n, inst_w, inst_e, reset);

parameter bw = 4;
parameter psum_bw = 16;

output [psum_bw-1:0] out_s;
input  [bw-1:0] in_w; // inst[1]:execute, inst[0]: kernel loading
output [bw-1:0] out_e; 
input  [1:0] inst_w;
output [1:0] inst_e;
input  [psum_bw-1:0] in_n;
input  clk;
input  reset;

wire [bw-1:0] in_w2;
wire [1:0] inst_w2;

mac_tile mac_t0 (
    .clk(clk),
    .reset(reset),
    .in_n(16'b0),
    .in_w(in_w),
    .out_s(),
    .out_e(in_w2),
    .inst_w(inst_w),
    .inst_e(inst_w2)
);

mac_tile mac_t1 (
    .clk(clk),
    .reset(reset),
    .in_n(16'b0),
    .in_w(in_w2),
    .out_s(),
    .out_e(out_e),
    .inst_w(inst_w2),
    .inst_e(inst_e)
);



endmodule

module mac_tile (clk, out_s, in_w, out_e, in_n, inst_w, inst_e, reset);

parameter bw = 4;
parameter psum_bw = 16;

output [psum_bw-1:0] out_s;
input  [bw-1:0] in_w; // inst[1]:execute, inst[0]: kernel loading
output [bw-1:0] out_e; 
input  [1:0] inst_w;
output [1:0] inst_e;
input  [psum_bw-1:0] in_n;
input  clk;
input  reset;

// Wire & Reg declaration   
wire [psum_bw-1:0] mac_out;
wire               act_reg_enable;
wire               w_reg_enable;
wire               psum_reg_enable;
wire               load_status;
wire               inst_reg0_enable,inst_reg1_enable,inst_q0_wire,inst_q1_wire;
reg                load_ready;
reg [bw -1:0]      a_q,b_q;
reg [psum_bw-1:0]  c_q;
reg [2:0]          inst_q;


// Assign Statements
assign out_e           = a_q;
assign out_s           = mac_out;
assign load_status     = inst_w[0] & load_ready;
assign act_reg_enable  = |inst_w;
assign w_reg_enable    = inst_w[0] & load_ready;
assign psum_reg_enable  = inst_w[1];
assign inst_reg0_enable = ~load_ready;
assign inst_reg1_enable = inst_w[1];
assign inst_q0_wire   = inst_q[0];
assign inst_q1_wire   = inst_q[1];
    
// Load Ready Register
    always @ (posedge clk) begin
        if (reset)
            load_ready <= 1'b1;
        else if (load_status)
            load_ready <= 1'b0;
    end

// Activation Register
    always @ (posedge clk) begin
        if (reset)
            a_q <= 'b0;
        else if (act_reg_enable)
            a_q <= in_w;
    end

// Weight Register
    always @ (posedge clk) begin
        if (reset)
            b_q <= 'b0;
        else if (w_reg_enable)
            b_q <= in_w;
    end

// Psum Register
    always @ (posedge clk) begin
        if (reset)
            c_q <= 'b0;
        else if (psum_reg_enable)
            c_q <= in_n;
    end
            
// Instruction Register   
    always @ (posedge clk) begin
        if (reset)
            inst_q <= 2'b0;
        else if (inst_reg0_enable)
            inst_q <= {inst_q1_wire,inst_w[0]};
        else if (inst_reg1_enable)
            inst_q <= {inst_w[1],inst_q0_wire};
    end

            
mac #(.bw(bw), .psum_bw(psum_bw)) mac_instance (
        .a(a_q), 
        .b(b_q),
        .c(c_q),
	.out(mac_out)
); 


endmodule


// Created by prof. Mingu Kang @VVIP Lab in UCSD ECE department
// Please do not spread this code without permission 
module mac (out, a, b, c);

parameter bw = 4;
parameter psum_bw = 16;

output signed [psum_bw-1:0] out;
input signed  [bw-1:0] a;  // activation
input signed  [bw-1:0] b;  // weight
input signed  [psum_bw-1:0] c;


wire signed [2*bw:0] product;
wire signed [psum_bw-1:0] psum;
wire signed [bw:0]   a_pad;

assign a_pad = {1'b0, a}; // force to be unsigned number
assign product = a_pad * b;

assign psum = product + c;
assign out = psum;

endmodule

1.ece284fa24_hw4/hardware/Rough work/mac_tb.vcd
$date
	Fri Nov  8 22:29:37 2024
$end
$version
	Icarus Verilog
$end
$timescale
	1s
$end
$scope module mac_array_tb $end
$var wire 2 ! inst_e [1:0] $end
$var wire 16 " out_s [15:0] $end
$var wire 4 # out_e [3:0] $end
$var parameter 32 $ bw $end
$var parameter 32 % psum_bw $end
$var reg 1 & clk $end
$var reg 16 ' in_n [15:0] $end
$var reg 4 ( in_w [3:0] $end
$var reg 2 ) inst_w [1:0] $end
$var reg 1 * reset $end
$scope module dut $end
$var wire 1 & clk $end
$var wire 16 + in_n [15:0] $end
$var wire 4 , in_w [3:0] $end
$var wire 2 - inst_e [1:0] $end
$var wire 2 . inst_w [1:0] $end
$var wire 2 / inst_w2 [1:0] $end
$var wire 16 0 out_s [15:0] $end
$var wire 1 * reset $end
$var wire 4 1 out_e [3:0] $end
$var wire 4 2 in_w2 [3:0] $end
$var parameter 32 3 bw $end
$var parameter 32 4 psum_bw $end
$scope module mac_t0 $end
$var wire 1 & clk $end
$var wire 16 5 in_n [15:0] $end
$var wire 4 6 in_w [3:0] $end
$var wire 2 7 inst_e [1:0] $end
$var wire 1 8 inst_reg0_enable $end
$var wire 2 9 inst_w [1:0] $end
$var wire 1 : load_status $end
$var wire 4 ; out_e [3:0] $end
$var wire 16 < out_s [15:0] $end
$var wire 1 * reset $end
$var wire 1 = w_reg_enable $end
$var wire 1 > psum_reg_enable $end
$var wire 16 ? mac_out [15:0] $end
$var wire 1 @ inst_reg1_enable $end
$var wire 1 A inst_q1_wire $end
$var wire 1 B inst_q0_wire $end
$var wire 1 C act_reg_enable $end
$var parameter 32 D bw $end
$var parameter 32 E psum_bw $end
$var reg 4 F a_q [3:0] $end
$var reg 4 G b_q [3:0] $end
$var reg 16 H c_q [15:0] $end
$var reg 3 I inst_q [2:0] $end
$var reg 1 J load_ready $end
$scope module mac_instance $end
$var wire 4 K a [3:0] $end
$var wire 4 L b [3:0] $end
$var wire 16 M c [15:0] $end
$var wire 16 N out [15:0] $end
$var wire 16 O psum [15:0] $end
$var wire 9 P product [8:0] $end
$var wire 5 Q a_pad [4:0] $end
$var parameter 32 R bw $end
$var parameter 32 S psum_bw $end
$upscope $end
$upscope $end
$scope module mac_t1 $end
$var wire 1 & clk $end
$var wire 16 T in_n [15:0] $end
$var wire 4 U in_w [3:0] $end
$var wire 2 V inst_e [1:0] $end
$var wire 1 W inst_reg0_enable $end
$var wire 2 X inst_w [1:0] $end
$var wire 1 Y load_status $end
$var wire 4 Z out_e [3:0] $end
$var wire 16 [ out_s [15:0] $end
$var wire 1 * reset $end
$var wire 1 \ w_reg_enable $end
$var wire 1 ] psum_reg_enable $end
$var wire 16 ^ mac_out [15:0] $end
$var wire 1 _ inst_reg1_enable $end
$var wire 1 ` inst_q1_wire $end
$var wire 1 a inst_q0_wire $end
$var wire 1 b act_reg_enable $end
$var parameter 32 c bw $end
$var parameter 32 d psum_bw $end
$var reg 4 e a_q [3:0] $end
$var reg 4 f b_q [3:0] $end
$var reg 16 g c_q [15:0] $end
$var reg 3 h inst_q [2:0] $end
$var reg 1 i load_ready $end
$scope module mac_instance $end
$var wire 4 j a [3:0] $end
$var wire 4 k b [3:0] $end
$var wire 16 l c [15:0] $end
$var wire 16 m out [15:0] $end
$var wire 16 n psum [15:0] $end
$var wire 9 o product [8:0] $end
$var wire 5 p a_pad [4:0] $end
$var parameter 32 q bw $end
$var parameter 32 r psum_bw $end
$upscope $end
$upscope $end
$upscope $end
$upscope $end
$enddefinitions $end
$comment Show the parameter values. $end
$dumpall
b10000 r
b100 q
b10000 d
b100 c
b10000 S
b100 R
b10000 E
b100 D
b10000 4
b100 3
b10000 %
b100 $
$end
#0
$dumpvars
b0xxxx p
bx o
bx n
bx m
bx l
bx k
bx j
xi
bx h
bx g
bx f
bx e
xb
xa
x`
z_
bx ^
z]
x\
bx [
bx Z
xY
bz X
xW
bz V
bx U
b0 T
b0xxxx Q
bx P
bx O
bx N
bx M
bx L
bx K
xJ
bx I
bx H
bx G
bx F
0C
xB
xA
0@
bx ?
0>
0=
bx <
bx ;
0:
b0 9
x8
bz 7
b1111 6
b0 5
bx 2
bx 1
bz 0
bz /
b0 .
bz -
b1111 ,
b0 +
1*
b0 )
b1111 (
b0 '
0&
bx #
bz "
bz !
$end
#5
08
0B
0A
0W
0a
0`
1J
b0 <
b0 ?
b0 N
b0 O
b0 P
b0 Q
b0 2
b0 ;
b0 U
b0 F
b0 K
b0 G
b0 L
b0 H
b0 M
b0 I
1i
b0 [
b0 ^
b0 m
b0 n
b0 o
b0 p
b0 #
b0 1
b0 Z
b0 e
b0 j
b0 f
b0 k
b0 g
b0 l
b0 h
1&
#10
0&
0*
#15
1&
#20
0&
1*
#25
1&
#30
1:
1=
0&
1C
b1 )
b1 .
b1 9
#35
1&
#40
0&
b1 (
b1 ,
b1 6
#45
1&
#50
0&
b1100 (
b1100 ,
b1100 6
#55
1&
#60
0&
b1101 (
b1101 ,
b1101 6
#65
1&
#70
0&
b1001 (
b1001 ,
b1001 6
#75
1&
#80
0&
b1111 (
b1111 ,
b1111 6
#85
1&
#90
0&
b1 (
b1 ,
b1 6
